sml_metadata/__init__.py
sml_metadata_that_some_guy-0.0.2.dist-info/LICENSE
sml_metadata_that_some_guy-0.0.2.dist-info/METADATA
sml_metadata_that_some_guy-0.0.2.dist-info/WHEEL
sml_metadata_that_some_guy-0.0.2.dist-info/top_level.txt
sml_metadata_that_some_guy-0.0.2.dist-info/RECORD
