Metadata-Version: 2.1
Name: sml-metadata-that-some-guy
Version: 0.0.2
Summary: a python script to be imported in ball_tracking.py,               a script that creates some random players in json format
Home-page: UNKNOWN
Author: Walid Khalladi
Author-email: walid.khalladi@hotmail.com
License: UNKNOWN
Platform: UNKNOWN
Classifier: Programming Language :: Python :: 3
Classifier: License :: OSI Approved :: MIT License
Classifier: Operating System :: OS Independent
